catvision/__init__.py
catvision/__version__.py
catvision/core.py
catvision/lowlight.py
catvision/motion.py
catvision/spatial.py
catvision/spectral.py
catvision/temporal.py
catvision/utils.py
catvision/validation.py
catvision/visualization.py
catvision-1.0.0.dist-info/licenses/LICENSE
catvision-1.0.0.dist-info/METADATA
catvision-1.0.0.dist-info/WHEEL
catvision-1.0.0.dist-info/top_level.txt
catvision-1.0.0.dist-info/RECORD
