Metadata-Version: 2.4
Name: catvision
Version: 1.0.0
Summary: Biologically accurate cat vision filter for neuroscience and visual perception research
Author-email: Arya Shah <arya.shah@iitgn.ac.in>
License: MIT
Project-URL: Homepage, https://github.com/aryashah2k/catvision
Project-URL: Documentation, https://catvision.readthedocs.io
Project-URL: Repository, https://github.com/aryashah2k/catvision
Project-URL: Issues, https://github.com/aryashah2k/catvision/issues
Keywords: cat vision,neuroscience,visual perception,image processing,animal vision,feline vision,retinal biology
Classifier: Development Status :: 4 - Beta
Classifier: Intended Audience :: Science/Research
Classifier: Topic :: Scientific/Engineering :: Image Processing
Classifier: Topic :: Scientific/Engineering :: Bio-Informatics
Classifier: License :: OSI Approved :: MIT License
Classifier: Programming Language :: Python :: 3
Classifier: Programming Language :: Python :: 3.8
Classifier: Programming Language :: Python :: 3.9
Classifier: Programming Language :: Python :: 3.10
Classifier: Programming Language :: Python :: 3.11
Classifier: Programming Language :: Python :: 3.12
Requires-Python: >=3.8
License-File: LICENSE
Requires-Dist: opencv-python-headless>=4.8.0
Requires-Dist: numpy>=1.24.0
Requires-Dist: scipy>=1.10.0
Requires-Dist: matplotlib>=3.7.0
Requires-Dist: Pillow>=10.0.0
Provides-Extra: dev
Requires-Dist: pytest>=7.4.0; extra == "dev"
Requires-Dist: pytest-cov>=4.1.0; extra == "dev"
Requires-Dist: black>=23.0.0; extra == "dev"
Requires-Dist: flake8>=6.0.0; extra == "dev"
Requires-Dist: mypy>=1.5.0; extra == "dev"
Dynamic: license-file
